type_valid/__init__.py
type_valid/type_valid.py
type_valid-0.1.5.dist-info/METADATA
type_valid-0.1.5.dist-info/WHEEL
type_valid-0.1.5.dist-info/top_level.txt
type_valid-0.1.5.dist-info/RECORD
