Metadata-Version: 2.1
Name: type-valid
Version: 0.1.5
Summary: Python Type validator with decorators
Home-page: https://github.com/edmhs/python-type-valid
Author: Eduards Marhelis
Author-email: eduards.marhelis@gmail.com
License: MIT
Platform: UNKNOWN
Classifier: Programming Language :: Python :: 3.5
Classifier: Programming Language :: Python :: 3.6
Classifier: Programming Language :: Python :: 3.7
Requires-Python: >=3.5.0
